pykafka_util/__init__.py
pykafka_util/pykafka_util.py
pykafka_util-1.0.1.dist-info/LICENSE
pykafka_util-1.0.1.dist-info/METADATA
pykafka_util-1.0.1.dist-info/WHEEL
pykafka_util-1.0.1.dist-info/top_level.txt
pykafka_util-1.0.1.dist-info/zip-safe
pykafka_util-1.0.1.dist-info/RECORD
