Metadata-Version: 2.1
Name: pykafka_util
Version: 1.0.1
Summary: kafka封装
Home-page: https://github.com/buyfakett
Author: buyfakett
Author-email: buyfakett@vip.qq.com
License: MIT
Requires-Python: >=3.6
License-File: LICENSE
Requires-Dist: confluent-kafka
